README.rst
setup.py
fa2l/__init__.py
fa2l/approximation.py
fa2l/fa2l.py
fa2l/force.py
fa2l/structures.py
fa2l.egg-info/PKG-INFO
fa2l.egg-info/SOURCES.txt
fa2l.egg-info/dependency_links.txt
fa2l.egg-info/requires.txt
fa2l.egg-info/top_level.txt