Metadata-Version: 1.0
Name: fa2l
Version: 0.1
Summary: Force Atlas 2 graph layout
Home-page: https://github.com/bosiakov/fa2l
Author: Eugene Bosiakov
Author-email: eugenebosyakov@gmail.com
License: UNKNOWN
Platform: UNKNOWN
